pykube/__init__.py
pykube/config.py
pykube/exceptions.py
pykube/http.py
pykube/mixins.py
pykube/objects.py
pykube/query.py
pykube/rolling_updater.py
pykube/session.py
pykube/utils.py
pykube-0.14.0.dist-info/DESCRIPTION.rst
pykube-0.14.0.dist-info/METADATA
pykube-0.14.0.dist-info/RECORD
pykube-0.14.0.dist-info/WHEEL
pykube-0.14.0.dist-info/metadata.json
pykube-0.14.0.dist-info/top_level.txt
test/__init__.py
test/test_config.py
test/test_http.py
test/test_httpclient.py
test/test_session.py
