Metadata-Version: 1.1
Name: pykube
Version: 0.14.0
Summary: Python client library for Kubernetes
Home-page: https://github.com/kelproject/pykube
Author: Eldarion, Inc.
Author-email: development@eldarion.com
License: Apache
Platform: UNKNOWN
Classifier: Development Status :: 3 - Alpha
Classifier: Environment :: Web Environment
Classifier: Intended Audience :: Developers
Classifier: License :: OSI Approved :: Apache Software License
Classifier: Operating System :: OS Independent
Classifier: Programming Language :: Python
